scholarium/__init__.py
scholarium/simple.py
scholarium-0.1.0.dist-info/WHEEL
scholarium-0.1.0.dist-info/METADATA
scholarium-0.1.0.dist-info/RECORD
