Metadata-Version: 2.1
Name: scholarium
Version: 0.1.0
Summary: Environment for scholarly computational books (compBook)
License: MIT
Author: Gerd Graßhoff
Author-email: gerd.grasshoff@opensciencetechnology.com
Requires-Python: >=3.8,<4.0
Classifier: License :: OSI Approved :: MIT License
Classifier: Programming Language :: Python :: 3
Classifier: Programming Language :: Python :: 3.8
Classifier: Programming Language :: Python :: 3.9
